pytmosph3r/__init__.py
pytmosph3r/__version__.py
pytmosph3r/aerosols.py
pytmosph3r/atmosphere/__init__.py
pytmosph3r/atmosphere/altitudeatmosphere.py
pytmosph3r/atmosphere/atmosphere.py
pytmosph3r/atmosphere/inputatmosphere.py
pytmosph3r/atmosphere/simple2d.py
pytmosph3r/chemistry/__init__.py
pytmosph3r/chemistry/ace3d.py
pytmosph3r/chemistry/chemistry.py
pytmosph3r/chemistry/dissociation.py
pytmosph3r/chemistry/fastchemistry.py
pytmosph3r/chemistry/interpolation.py
pytmosph3r/chemistry/standard.py
pytmosph3r/cli/__init__.py
pytmosph3r/cli/interface_h5_to_nc.py
pytmosph3r/cli/interface_nc_to_h5.py
pytmosph3r/cli/interface_nc_to_nc.py
pytmosph3r/cli/p3.py
pytmosph3r/cli/parser.py
pytmosph3r/config/__init__.py
pytmosph3r/config/factory.py
pytmosph3r/config/readconfig.py
pytmosph3r/external/__init__.py
pytmosph3r/external/fastchem.pxd
pytmosph3r/external/fastchem.pyx
pytmosph3r/grid.py
pytmosph3r/interface/__init__.py
pytmosph3r/interface/hdf5.py
pytmosph3r/interface/io.py
pytmosph3r/interface/netcdf.py
pytmosph3r/log/__init__.py
pytmosph3r/log/logger.py
pytmosph3r/model/ATMOmodel.py
pytmosph3r/model/__init__.py
pytmosph3r/model/diagfimodel.py
pytmosph3r/model/hdf5model.py
pytmosph3r/model/model.py
pytmosph3r/observations/__init__.py
pytmosph3r/observations/emission.py
pytmosph3r/observations/lightcurve.py
pytmosph3r/observations/limbdarkening.py
pytmosph3r/observations/parallel.py
pytmosph3r/observations/phasecurve.py
pytmosph3r/observations/transmission.py
pytmosph3r/opacity.py
pytmosph3r/planetary_system/__init__.py
pytmosph3r/planetary_system/observer.py
pytmosph3r/planetary_system/orbit/__init__.py
pytmosph3r/planetary_system/orbit/base.py
pytmosph3r/planetary_system/orbit/orbit_circular.py
pytmosph3r/planetary_system/planet.py
pytmosph3r/planetary_system/star/__init__.py
pytmosph3r/planetary_system/star/base.py
pytmosph3r/planetary_system/star/star_blackbody.py
pytmosph3r/planetary_system/star/star_spectrum.py
pytmosph3r/plot/__init__.py
pytmosph3r-2.3.0.dist-info/LICENSE
pytmosph3r-2.3.0.dist-info/METADATA
pytmosph3r-2.3.0.dist-info/WHEEL
pytmosph3r-2.3.0.dist-info/entry_points.txt
pytmosph3r-2.3.0.dist-info/RECORD
